bavard_ml_common/__init__.py
bavard_ml_common/gcp/__init__.py
bavard_ml_common/gcp/gcs.py
bavard_ml_common/gcp/pub_sub.py
bavard_ml_common/ml/__init__.py
bavard_ml_common/ml/dataset.py
bavard_ml_common/ml/utils.py
bavard_ml_common/persistence/__init__.py
bavard_ml_common/persistence/artifact_manager.py
bavard_ml_common/persistence/record_store/__init__.py
bavard_ml_common/persistence/record_store/base.py
bavard_ml_common/persistence/record_store/firestore.py
bavard_ml_common/persistence/record_store/memory.py
bavard_ml_common/persistence/serialization.py
bavard_ml_common/types/__init__.py
bavard_ml_common/types/agent.py
bavard_ml_common/types/conversations/__init__.py
bavard_ml_common/types/conversations/actions.py
bavard_ml_common/types/conversations/conversation.py
bavard_ml_common/types/conversations/dialogue_turns.py
bavard_ml_common/types/data.py
bavard_ml_common/types/ml.py
bavard_ml_common/types/nlu.py
bavard_ml_common/types/utils.py
bavard_ml_common/utils.py
bavard_ml_common/web/__init__.py
bavard_ml_common/web/errors.py
bavard_ml_common/web/web_service.py
bavard_ml_common-0.1.21.dist-info/WHEEL
bavard_ml_common-0.1.21.dist-info/METADATA
bavard_ml_common-0.1.21.dist-info/RECORD
